pytest_httpchain_models/__init__.py
pytest_httpchain_models/entities.py
pytest_httpchain_models/types.py
pytest_httpchain_models-0.2.1.dist-info/WHEEL
pytest_httpchain_models-0.2.1.dist-info/METADATA
pytest_httpchain_models-0.2.1.dist-info/RECORD
