Metadata-Version: 2.3
Name: pytest-httpchain-models
Version: 0.2.1
Summary: Pydantic models for pytest-httpchain
Author: Alexander Eresov
Author-email: Alexander Eresov <aeresov@gmail.com>
Requires-Dist: jmespath>=1.0.0
Requires-Dist: jsonschema>=4.0.0
Requires-Dist: graphql-core>=3.0.0
Requires-Dist: pytest-httpchain-templates
Requires-Dist: pytest-httpchain-userfunc
Requires-Python: >=3.13
